gancho/__init__.py
gancho/__main__.py
gancho/core.py
gancho/utils.py
gancho-0.1.5.dist-info/METADATA
gancho-0.1.5.dist-info/WHEEL
gancho-0.1.5.dist-info/entry_points.txt
gancho-0.1.5.dist-info/RECORD
