Metadata-Version: 2.4
Name: gancho
Version: 0.1.5
Summary: Gancho receives webhooks and triggers actions in response.
Project-URL: repository, https://github.com/rochacbruno/python-devops-linuxtips/tree/main/projetos/gancho
Author-email: Bruno Rocha <rochacbruno@gmail.com>
License: AGPL-3.0
Keywords: automation,http,webhooks
Requires-Python: >=3.10
Requires-Dist: fastapi>=0.117.1
Requires-Dist: httpx>=0.28.1
Requires-Dist: uvicorn[standard]>=0.37.0
